luoluo/__init__.py
luoluo/add.py
luoluo/division.py
luoluo/multiply.py
luoluo/sqrt.py
luoluo/subtract.py
luoluo-1.0.dist-info/METADATA
luoluo-1.0.dist-info/RECORD
luoluo-1.0.dist-info/WHEEL
luoluo-1.0.dist-info/top_level.txt
